hello_g/__init__.py
hello_g-0.1.5.dist-info/WHEEL
hello_g-0.1.5.dist-info/METADATA
hello_g-0.1.5.dist-info/RECORD
